{"algorithmStatistics":{"Naïve":{"count":2069,"min":51921,"max":7462293,"mean":404078.0,"standardDeviation":415450.2911448554},"Boyer-Moore":{"count":2069,"min":48228,"max":2394075,"mean":170830.0,"standardDeviation":146419.2141377566},"Simon":{"count":2069,"min":56882,"max":3282156,"mean":281709.0,"standardDeviation":260938.0995787024},"Morris-Pratt":{"count":2069,"min":55914,"max":5877479,"mean":297714.0,"standardDeviation":322450.51400038373},"Knuth-Morris-Pratt":{"count":2069,"min":57896,"max":31629738,"mean":1090377.0,"standardDeviation":2401547.239469027},"Bitap":{"count":2069,"min":51162,"max":2790377,"mean":263509.0,"standardDeviation":234544.70187257158}},"testRunStatistics":{"e88291841430":{"count":12414,"min":48228,"max":31629738,"mean":418036.0,"standardDeviation":1061353.7162988745}},"inputFileStatistics":{"resources/tcpdump.pcap":{"count":12186,"min":48228,"max":31629738,"mean":419878.0,"standardDeviation":1067319.4314972018},"resources/dns.cap":{"count":228,"min":86626,"max":6946643,"mean":319602.0,"standardDeviation":661717.3940313528}},"overallStatistics":{"count":12414,"min":48228,"max":31629738,"mean":418036.0,"standardDeviation":1061353.7162988745}}