{"algorithmStatistics":{"Naïve":{"count":2031,"min":71146,"max":48418528,"mean":1205500.0,"standardDeviation":2630365.4949814035},"Knuth-Morris-Pratt":{"count":2031,"min":68489,"max":13210380,"mean":306103.0,"standardDeviation":492075.4038183174}},"testRunStatistics":{"9704ed8a344c":{"count":4062,"min":68489,"max":48418528,"mean":755802.0,"standardDeviation":1944918.8505055155}},"inputFileStatistics":{"resources/tcpdump.pcap":{"count":4062,"min":68489,"max":48418528,"mean":755802.0,"standardDeviation":1944918.8505055155}},"overallStatistics":{"count":4062,"min":68489,"max":48418528,"mean":755802.0,"standardDeviation":1944918.8505055155}}